pysaleryd/__init__.py
pysaleryd/client.py
pysaleryd/const.py
pysaleryd/data.py
pysaleryd/py.typed
pysaleryd/helpers/__init__.py
pysaleryd/helpers/error_cache.py
pysaleryd/helpers/task.py
pysaleryd/helpers/websocket.py
pysaleryd-7.3.2.dist-info/licenses/LICENSE.txt
pysaleryd-7.3.2.dist-info/METADATA
pysaleryd-7.3.2.dist-info/WHEEL
pysaleryd-7.3.2.dist-info/top_level.txt
pysaleryd-7.3.2.dist-info/RECORD
